pytest_springfield/__init__.py
pytest_springfield/assertrepr_compare.py
springfield/__init__.py
springfield/alias.py
springfield/entity.py
springfield/fields.py
springfield/timeutil.py
springfield/types.py
springfield-0.9.1.dist-info/LICENSE
springfield-0.9.1.dist-info/METADATA
springfield-0.9.1.dist-info/WHEEL
springfield-0.9.1.dist-info/entry_points.txt
springfield-0.9.1.dist-info/top_level.txt
springfield-0.9.1.dist-info/RECORD
