Metadata-Version: 2.1
Name: springfield
Version: 0.9.1
Summary: A backend agnostic data modeling entity library
Home-page: http://springfield.readthedocs.org
Author: Mike Thornton
Author-email: six8@devdetails.com
License: BSD
Download-URL: http://github.com/plynth/springfield
Keywords: orm
Platform: UNKNOWN
Classifier: Programming Language :: Python
Classifier: Intended Audience :: Developers
Classifier: Natural Language :: English
Classifier: Topic :: Software Development :: Libraries :: Python Modules
Classifier: Programming Language :: Python
Classifier: Programming Language :: Python :: 2.7
Classifier: Programming Language :: Python :: 3
Classifier: Programming Language :: Python :: 3.6
Classifier: Programming Language :: Python :: 3.7
Classifier: Operating System :: OS Independent
Classifier: License :: OSI Approved :: BSD License
Requires-Dist: anticipate (>=0.9.1)
Requires-Dist: six (>=1.9.0)
